hand2text/__init__.py
hand2text/cli.py
hand2text/combine_texts.py
hand2text/llm/__init__.py
hand2text/llm/refine.py
hand2text/llm/vision_llm.py
hand2text/main.py
hand2text/ocr/__init__.py
hand2text/ocr/ocr.py
hand2text/pdf2img/__init__.py
hand2text/pdf2img/converter.py
hand2text-0.1.2.dist-info/entry_points.txt
hand2text-0.1.2.dist-info/METADATA
hand2text-0.1.2.dist-info/WHEEL
hand2text-0.1.2.dist-info/RECORD
