Metadata-Version: 2.1
Name: hand2text
Version: 0.1.2
Summary: Convert handwritten PDF notes to text using OCR and LLM
Home-page: https://github.com/alihaskar/hand2text
Keywords: ocr,handwriting,pdf,text-extraction,ai
Author: ali askar
Author-email: 26202651+alihaskar@users.noreply.github.com
Requires-Python: >=3.10,<4.0
Classifier: Development Status :: 3 - Alpha
Classifier: Intended Audience :: Developers
Classifier: License :: OSI Approved :: MIT License
Classifier: Programming Language :: Python :: 3
Classifier: Programming Language :: Python :: 3.10
Classifier: Programming Language :: Python :: 3.11
Classifier: Programming Language :: Python :: 3.12
Requires-Dist: openai (>=1.76.0,<2.0.0)
Requires-Dist: pillow (>=11.2.1,<12.0.0)
Requires-Dist: pymupdf (>=1.25.5,<2.0.0)
Requires-Dist: pytesseract (>=0.3.13,<0.4.0)
Requires-Dist: python-dotenv (>=1.1.0,<2.0.0)
Project-URL: Repository, https://github.com/alihaskar/hand2text
